agentdojo/__init__.py
agentdojo/ast_utils.py
agentdojo/base_tasks.py
agentdojo/benchmark.py
agentdojo/functions_runtime.py
agentdojo/logging.py
agentdojo/models.py
agentdojo/strenum.py
agentdojo/types.py
agentdojo/yaml_loader.py
agentdojo/agent_pipeline/__init__.py
agentdojo/agent_pipeline/agent_pipeline.py
agentdojo/agent_pipeline/base_pipeline_element.py
agentdojo/agent_pipeline/basic_elements.py
agentdojo/agent_pipeline/errors.py
agentdojo/agent_pipeline/ground_truth_pipeline.py
agentdojo/agent_pipeline/pi_detector.py
agentdojo/agent_pipeline/planner.py
agentdojo/agent_pipeline/tool_execution.py
agentdojo/agent_pipeline/llms/__init__.py
agentdojo/agent_pipeline/llms/anthropic_llm.py
agentdojo/agent_pipeline/llms/cohere_llm.py
agentdojo/agent_pipeline/llms/google_llm.py
agentdojo/agent_pipeline/llms/local_llm.py
agentdojo/agent_pipeline/llms/openai_llm.py
agentdojo/agent_pipeline/llms/prompting_llm.py
agentdojo/attacks/__init__.py
agentdojo/attacks/attack_registry.py
agentdojo/attacks/base_attacks.py
agentdojo/attacks/baseline_attacks.py
agentdojo/attacks/dos_attacks.py
agentdojo/attacks/important_instructions_attacks.py
agentdojo/data/system_messages.yaml
agentdojo/data/suites/banking/environment.yaml
agentdojo/data/suites/banking/injection_vectors.yaml
agentdojo/data/suites/slack/environment.yaml
agentdojo/data/suites/slack/injection_vectors.yaml
agentdojo/data/suites/travel/environment.yaml
agentdojo/data/suites/travel/injection_vectors.yaml
agentdojo/data/suites/workspace/environment.yaml
agentdojo/data/suites/workspace/gpt_prompts.txt
agentdojo/data/suites/workspace/injection_vectors.yaml
agentdojo/data/suites/workspace/include/calendar.yaml
agentdojo/data/suites/workspace/include/cloud_drive.yaml
agentdojo/data/suites/workspace/include/inbox.yaml
agentdojo/default_suites/__init__.py
agentdojo/default_suites/v1/__init__.py
agentdojo/default_suites/v1/banking/__init__.py
agentdojo/default_suites/v1/banking/injection_tasks.py
agentdojo-0.1.34.dist-info/METADATA
agentdojo-0.1.34.dist-info/WHEEL
agentdojo-0.1.34.dist-info/licenses/LICENSE
agentdojo-0.1.34.dist-info/RECORD
