Metadata-Version: 2.4
Name: agentdojo
Version: 0.1.34
Summary: A Dynamic Environment to Evaluate Attacks and Defenses for LLM Agents
Project-URL: homepage, https://agentdojo.spylab.ai
Project-URL: repository, https://github.com/ethz-spylab/agentdojo
Project-URL: documentation, https://agentdojo.spylab.ai/api/agent_pipeline/basic_elements/
Project-URL: issues, https://github.com/ethz-spylab/agentdojo/issues
Author-email: Edoardo Debenedetti <edoardo.debenedetti@inf.ethz.ch>, Jie Zhang <jie.zhang@inf.ethz.ch>, Mislav Balunovic <mislav.balunovic@inf.ethz.ch>, Luca Beurer-Kellner <luca.beurer-kellner@inf.ethz.ch>
Maintainer-email: Edoardo Debenedetti <edoardo.debenedetti@inf.ethz.ch>
License-File: LICENSE
Keywords: benchmark,llms,machine learning,prompt injection,security
Classifier: Development Status :: 4 - Beta
Classifier: Environment :: GPU
Classifier: Intended Audience :: Developers
Classifier: Intended Audience :: Science/Research
Classifier: License :: OSI Approved :: MIT License
Classifier: Programming Language :: Python :: 3
Classifier: Programming Language :: Python :: 3.10
Classifier: Programming Language :: Python :: 3.11
Classifier: Programming Language :: Python :: 3.12
Classifier: Topic :: Scientific/Engineering :: Artificial Intelligence
Classifier: Topic :: Security
Requires-Python: >=3.10
Requires-Dist: anthropic>=0.47.0
Requires-Dist: click>=8.1.7
Requires-Dist: cohere>=5.3.4
Requires-Dist: deepdiff>=7.0.1
Requires-Dist: docstring-parser>=0.15
Requires-Dist: google-genai>=1.15.0
Requires-Dist: langchain>=0.1.17
Requires-Dist: openai>=1.59.7
Requires-Dist: pydantic[email]>=2.7.1
Requires-Dist: python-dotenv>=1.0.1
Requires-Dist: pyyaml>=6.0.1
Requires-Dist: rich>=13.7.1
Requires-Dist: tenacity>=8.2.3
Requires-Dist: typing-extensions>=4.11.0
Provides-Extra: transformers
Requires-Dist: torch>=2.2.1; extra == 'transformers'
Requires-Dist: transformers>=4.41.2; extra == 'transformers'
